awsibox/RP.py
awsibox/__init__.py
awsibox/args.py
awsibox/cfg.py
awsibox/cfg_instance_types.py
awsibox/discover.py
awsibox/generate.py
awsibox/override.py
awsibox/shared.py
awsibox/aws/CloudFormationResourceSpecification.json
awsibox/cfg/ibox/com/common.yml
awsibox/cfg/ibox/com/autoscaling/autoscalinggroup-elasticloadbalancing.yml
awsibox/cfg/ibox/com/autoscaling/capacity.yml
awsibox/cfg/ibox/com/autoscaling/cloudwatch-agent.yml
awsibox/cfg/ibox/com/autoscaling/ephemeral.yml
awsibox/cfg/ibox/com/autoscaling/imageid-ec2.yml
awsibox/cfg/ibox/com/autoscaling/imageid-ecs.yml
awsibox/cfg/ibox/com/autoscaling/mixed_instances.yml
awsibox/cfg/ibox/com/autoscaling/spot-asg.yml
awsibox/cfg/ibox/com/autoscaling/spot-auto.yml
awsibox/cfg/ibox/com/autoscaling/termination-policies.yml
awsibox/cfg/ibox/com/certificatemanager/certificate-regional.yml
awsibox/cfg/ibox/com/cloudfront/custom-errors.yml
awsibox/cfg/ibox/com/cloudfront/for-services.yml
awsibox/cfg/ibox/com/cloudfront/i_base.yml
awsibox/cfg/ibox/com/cloudfront/origin-adhoc.yml
awsibox/cfg/ibox/com/cloudfront/origin-vpc.yml
awsibox/cfg/ibox/com/codedeploy/deployment-group.yml
awsibox/cfg/ibox/com/dynamodb/table-credstash.yml
awsibox/cfg/ibox/com/ec2/bottlerocket.yml
awsibox/cfg/ibox/com/ec2/securitygroup.yml
awsibox/cfg/ibox/com/ec2/securitygroups-base.yml
awsibox/cfg/ibox/com/ecs/capacityprovider.yml
awsibox/cfg/ibox/com/ecs/daemon-reserver-cpu.yml
awsibox/cfg/ibox/com/ecs/fargate-spot.yml
awsibox/cfg/ibox/com/ecs/service-and-cluster.yml
awsibox/cfg/ibox/com/ecs/service-and-eventer-scheduled-task.yml
awsibox/cfg/ibox/com/ecs/service-elasticloadbalancing.yml
awsibox/cfg/ibox/com/ecs/task.yml
awsibox/cfg/ibox/com/ecs/taskdefinition-volume.yml
awsibox/cfg/ibox/com/efs/accesspoint-app.yml
awsibox/cfg/ibox/com/elasticloadbalancing/accountid.yml
awsibox/cfg/ibox/com/elasticloadbalancing/certificate-adhoc.yml
awsibox/cfg/ibox/com/elasticloadbalancing/hostedzoneid.yml
awsibox/cfg/ibox/com/elasticloadbalancing/i_base.yml
awsibox.egg-info/PKG-INFO
awsibox.egg-info/SOURCES.txt
awsibox.egg-info/dependency_links.txt
awsibox.egg-info/requires.txt
awsibox.egg-info/top_level.txt
awsibox-1.0.0.dist-info/LICENSE
awsibox-1.0.0.dist-info/METADATA
awsibox-1.0.0.dist-info/WHEEL
awsibox-1.0.0.dist-info/top_level.txt
awsibox-1.0.0.dist-info/RECORD
